api_utils/__init__.py
api_utils/base_model.py
api_utils/constants.py
api_utils/database.py
api_utils/query.py
api_utils/qurey.py
api_utils/utils.py
apps/__init__.py
apps/data_api.py
apps/entities.py
apps/entities_api.py
apps/players_api.py
apps/ranking_api.py
common/__init__.py
common/base_model.py
common/constants.py
common/database.py
router/__init__.py
router/data.py
router/entities.py
router/players.py
router/ranking.py
rr_api_beta-4.11.dist-info/LICENSE
rr_api_beta-4.11.dist-info/METADATA
rr_api_beta-4.11.dist-info/WHEEL
rr_api_beta-4.11.dist-info/top_level.txt
rr_api_beta-4.11.dist-info/RECORD
