Metadata-Version: 2.1
Name: rr-api-beta
Version: 4.11
Summary: rr-api
Home-page: https://upload.pypi.org/legacy/
Author: RR Team
Author-email: rr@rr.com
License: MIT
Platform: UNKNOWN
Classifier: Programming Language :: Python :: 3
Classifier: License :: OSI Approved :: MIT License
Classifier: Operating System :: OS Independent
Requires-Python: >=3.10
License-File: LICENSE
Requires-Dist: rr-common-base (==1.0)
Requires-Dist: fastapi (~=0.75.0)
Requires-Dist: uvicorn
